{
    "items":[
        {
            "genre":true,
            "thumb":"https://file.kinolights.com/m/content_poster/202307/12/5aead46a-3993-48bb-89dc-5fb09b52827e.webp",
            "recommRate":100.0,
            "title":"내가 예뻐진 그 여름",
            "sort":"1,2"
        },
        {
            "genre":false,
            "thumb":"https://file.kinolights.com/m/content_poster/202307/12/abf44ac4-1644-409c-b1a8-686c852f371d.webp",
            "recommRate":91.2,
            "title":"애프터 양",
            "sort":"2,3"
        },
        {
            "genre":false,
            "thumb":"https://file.kinolights.com/m/content_poster/202307/12/08a615bb-d808-4b5c-94d6-fd49407b9da7.webp",
            "recommRate":80.7,
            "title":"무뢰한",
            "sort":"2,3"
        },
        {
            "genre":true,
            "thumb":"https://file.kinolights.com/m/content_poster/202307/12/b8f38458-3476-493e-9813-16a94225ac14.webp",
            "recommRate":80.7,
            "title":"오월의 청춘",
            "sort":"1,3"
        },
        {
            "genre":false,
            "thumb":"https://file.kinolights.com/m/content_poster/202307/12/2d1b0169-063a-4176-914c-4bc701c7a0c2.webp",
            "recommRate":96.7,
            "title":"꽃다발 같은 사랑을 했다",
            "sort":"1,3"
        },
        {
            "genre":true,
            "thumb":"https://file.kinolights.com/m/content_poster/202307/12/26319e63-49ae-438d-8916-179cde60c5e6.webp",
            "recommRate":93.1,
            "title":"소년을 위로해줘!",
            "sort":"1,2"
        },
        {
            "genre":false,
            "thumb":"https://file.kinolights.com/m/content_poster/202307/12/fb71c3a7-f7c7-45cb-9264-da42d53cefb9.webp",
            "recommRate":89.5,
            "title":"루터: 태양의 몰락",
            "sort":"2"
        },
        {
            "genre":false,
            "thumb":"https://file.kinolights.com/m/content_poster/202307/12/4167c3e3-6135-41d3-b625-cf058f21a1c8.webp",
            "recommRate":25.6,
            "title":"화유기",
            "sort":"1,2,3"
        },
        {
            "genre":false,
            "thumb":"https://file.kinolights.com/m/content_poster/202307/12/4843d48e-082e-4123-89f7-0b8d6d5bb448.webp",
            "recommRate":92.7,
            "title":"사랑할 땐 누구나 최악이 된다",
            "sort":"1,2"
        },
        {
            "genre":false,
            "thumb":"https://file.kinolights.com/m/content_poster/202309/06/3df4a834-3490-4220-935c-20ffb204bc2e.webp",
            "recommRate":83.2,
            "title":"언어의 정원",
            "sort":"3"
        }
    ] 
} 